Workbook

Sheet Assumptions
B1: Music Royalty Stream DCF Valuation Model
B2: Independent Artist Catalog Analysis
B3: Prepared by: Dhruva Lepakshi
B5: Catalog Overview
B6: Artist Name | C6: Drake
B7: Total Tracks in Catalog | C7: 750
B8: Catalog Age (Years) | C8: 8
B9: Rights Type | C9: Both
B10: Ownership Share (%) | C10: 0.75 | F10: 75% ownership after label/distributor split (UMG/OVO)
B12: LTM Streaming Data by DSP
B13: DSP (Platform) | C13: LTM Streams | D13: Avg Per-Stream Rate ($) | E13: LTM Revenue ($)
B14: Spotify | C14: 18800000000 | D14: 0.004 | E14: =C14*D14 -> 75200000
B15: Apple Music | C15: 6500000000 | D15: 0.01 | E15: =C15*D15 -> 65000000
B16: YouTube Music | C16: 8000000000 | D16: 0.002 | E16: =C16*D16 -> 16000000
B17: Amazon Music | C17: 3200000000 | D17: 0.005 | E17: =C17*D17 -> 16000000
B18: Tidal | C18: 800000000 | D18: 0.013 | E18: =C18*D18 -> 10400000
B19: Other DSPs | C19: 1500000000 | D19: 0.003 | E19: =C19*D19 -> 4500000
B20: Total | C20: =SUM(C14:C19) -> 38800000000 | D20: =IF(C20=0,0,E20/C20) -> 0.0048221649 | E20: =SUM(E14:E19) -> 187100000
F21: Blended PSR = Total Revenue / Total Streams (weighted average)
B23: DSP Mix Analysis
B24: DSP | C24: Stream Share (%) | D24: Revenue Share (%) | E24: PSR vs. Blended
B25: Spotify | C25: =IF(C20=0,0,C14/C20) -> 0.48453608 | D25: =IF(E20=0,0,E14/E20) -> 0.4019241 | E25: =IF(D20=0,0,D14/D20) -> 0.82950294
B26: Apple Music | C26: =IF(C20=0,0,C15/C20) -> 0.16752577 | D26: =IF(E20=0,0,E15/E20) -> 0.3474078 | E26: =IF(D20=0,0,D15/D20) -> 2.0737573
B27: YouTube Music | C27: =IF(C20=0,0,C16/C20) -> 0.20618557 | D27: =IF(E20=0,0,E16/E20) -> 0.085515767 | E27: =IF(D20=0,0,D16/D20) -> 0.41475147
B28: Amazon Music | C28: =IF(C20=0,0,C17/C20) -> 0.082474227 | D28: =IF(E20=0,0,E17/E20) -> 0.085515767 | E28: =IF(D20=0,0,D17/D20) -> 1.0368787
B29: Tidal | C29: =IF(C20=0,0,C18/C20) -> 0.020618557 | D29: =IF(E20=0,0,E18/E20) -> 0.055585249 | E29: =IF(D20=0,0,D18/D20) -> 2.6958846
B30: Other DSPs | C30: =IF(C20=0,0,C19/C20) -> 0.038659794 | D30: =IF(E20=0,0,E19/E20) -> 0.024051309 | E30: =IF(D20=0,0,D19/D20) -> 0.6221272
B32: Projection Assumptions
B33: Projection Period (Years) | C33: 10 | F33: Typical: 10 years for music royalties
B34: Stream Decay Rate — Years 1-3 (%) | C34: -0.03 | F34: Annual % change in streams; enter negative for decline (e.g. -5.0%)
B35: Stream Decay Rate — Years 4-7 (%) | C35: -0.06 | F35: Streams typically decay faster as catalog ages
B36: Stream Decay Rate — Years 8-10 (%) | C36: -0.08 | F36: Long-tail; older catalogs may stabilize here
B37: Annual PSR Growth Rate (%) | C37: 0.02 | F37: Driven by DSP subscription price increases (~1-3%)
B38: Discount Rate / WACC (%) | C38: 0.1 | F38: Typical: 10-15% for music royalties (illiquid asset)
B39: Terminal Growth Rate (%) | C39: -0.02 | F39: Perpetual rate for terminal value; usually negative (-2% to 0%)

Sheet DCF Model
B1: Discounted Cash Flow Model — Music Royalty Streams
B2: All formulas are pre-built — they pull from the Assumptions tab automatically
B4: Metric | C4: LTM (Base) | D4: Year 1 | E4: Year 2 | F4: Year 3 | G4: Year 4 | H4: Year 5 | I4: Year 6 | J4: Year 7 | K4: Year 8 | L4: Year 9 | M4: Year 10
B5: Total Streams | C5: =Assumptions!C20 -> 38800000000 | D5: =C5*(1+Assumptions!C30) -> 40300000000 | E5: =D5*(1+Assumptions!D30) -> 41269267771 | F5: =E5*(1+Assumptions!E30) -> 66944001970 | G5: =F5*(1+Assumptions!F30) -> 66944001970 | H5: =G5*(1+Assumptions!G30) -> 66944001970 | I5: =H5*(1+Assumptions!H30) -> 66944001970 | J5: =I5*(1+Assumptions!I30) -> 66944001970 | K5: =J5*(1+Assumptions!J30) -> 66944001970 | ... M5: =L5*(1+Assumptions!L30) -> 66944001970
B6: Stream Growth (%) | C6: — | D6: =IF(C5=0,0,(D5-C5)/C5) -> 0.038659794 | E6: =IF(D5=0,0,(E5-D5)/D5) -> 0.024051309 | F6: =IF(E5=0,0,(F5-E5)/E5) -> 0.6221272 | G6: =IF(F5=0,0,(G5-F5)/F5) -> 0 | H6: =IF(G5=0,0,(H5-G5)/G5) -> 0 | I6: =IF(H5=0,0,(I5-H5)/H5) -> 0 | J6: =IF(I5=0,0,(J5-I5)/I5) -> 0 | K6: =IF(J5=0,0,(K5-J5)/J5) -> 0 | ... M6: =IF(L5=0,0,(M5-L5)/L5) -> 0
B7: Blended Per-Stream Rate ($) | C7: =Assumptions!D20 -> 0.0048221649 | D7: =C7*(1+Assumptions!C37) -> 0.0049186082 | E7: =D7*(1+Assumptions!C37) -> 0.0050169804 | F7: =E7*(1+Assumptions!C37) -> 0.00511732 | G7: =F7*(1+Assumptions!C37) -> 0.0052196664 | H7: =G7*(1+Assumptions!C37) -> 0.0053240597 | I7: =H7*(1+Assumptions!C37) -> 0.0054305409 | J7: =I7*(1+Assumptions!C37) -> 0.0055391518 | K7: =J7*(1+Assumptions!C37) -> 0.0056499348 | L7: =K7*(1+Assumptions!C37) -> 0.0057629335 | M7: =L7*(1+Assumptions!C37) -> 0.0058781922
B8: Gross Royalty Revenue ($) | C8: =Assumptions!E20 -> 187100000 | D8: =D5*D7 -> 1.9821991e+08 | E8: =E5*E7 -> 207047108 | F8: =F5*F7 -> 3.4257388e+08 | G8: =G5*G7 -> 3.4942536e+08 | H8: =H5*H7 -> 3.5641387e+08 | I8: =I5*I7 -> 3.6354214e+08 | J8: =J5*J7 -> 3.7081299e+08 | K8: =K5*K7 -> 3.7822925e+08 | ... M8: =M5*M7 -> 3.9350971e+08
B9: Net Revenue (After Ownership %) | C9: =C8*Assumptions!C10 -> 140325000 | D9: =D8*Assumptions!C10 -> 1.4866493e+08 | E9: =E8*Assumptions!C10 -> 155285331 | F9: =F8*Assumptions!C10 -> 2.5693041e+08 | G9: =G8*Assumptions!C10 -> 2.6206902e+08 | H9: =H8*Assumptions!C10 -> 2.673104e+08 | I9: =I8*Assumptions!C10 -> 2.7265661e+08 | J9: =J8*Assumptions!C10 -> 2.7810974e+08 | K9: =K8*Assumptions!C10 -> 2.8367193e+08 | L9: =L8*Assumptions!C10 -> 2.8934537e+08 | M9: =M8*Assumptions!C10 -> 2.9513228e+08
B10: Revenue Growth (%) | C10: — | D10: =IF(C9=0,0,(D9-C9)/C9) -> 0.05943299 | E10: =IF(D9=0,0,(E9-D9)/D9) -> 0.044532336 | F10: =IF(E9=0,0,(F9-E9)/E9) -> 0.65456975 | G10: =IF(F9=0,0,(G9-F9)/F9) -> 0.02 | H10: =IF(G9=0,0,(H9-G9)/G9) -> 0.02 | I10: =IF(H9=0,0,(I9-H9)/H9) -> 0.02 | J10: =IF(I9=0,0,(J9-I9)/I9) -> 0.02 | K10: =IF(J9=0,0,(K9-J9)/J9) -> 0.02 | ... M10: =IF(L9=0,0,(M9-L9)/L9) -> 0.02
B12: Discounting
B13: Discount Rate (WACC) | C13: =Assumptions!C38 -> 0.1
B14: Discount Factor | C14: — | D14: =1/(1+Assumptions!C38)^1 -> 0.90909091 | E14: =1/(1+Assumptions!C38)^2 -> 0.82644628 | F14: =1/(1+Assumptions!C38)^3 -> 0.7513148 | G14: =1/(1+Assumptions!C38)^4 -> 0.68301346 | H14: =1/(1+Assumptions!C38)^5 -> 0.62092132 | I14: =1/(1+Assumptions!C38)^6 -> 0.56447393 | J14: =1/(1+Assumptions!C38)^7 -> 0.51315812 | K14: =1/(1+Assumptions!C38)^8 -> 0.46650738 | L14: =1/(1+Assumptions!C38)^9 -> 0.42409762 | M14: =1/(1+Assumptions!C38)^10 -> 0.38554329
B15: PV of Royalty Cash Flow ($) | C15: — | D15: =D9*D14 -> 1.3514994e+08 | E15: =E9*E14 -> 1.2833498e+08 | F15: =F9*F14 -> 1.9303562e+08 | G15: =G9*G14 -> 1.7899667e+08 | H15: =H9*H14 -> 1.6597873e+08 | I15: =I9*I14 -> 1.5390755e+08 | J15: =J9*J14 -> 1.4271427e+08 | K15: =K9*K14 -> 1.3233505e+08 | ... M15: =M9*M14 -> 1.1378627e+08
B17: Valuation Summary
B18: Sum of PV of Projected Cash Flows ($) | C18: =SUM(D15:M15) -> 1466949762
B19: Terminal Value (Gordon Growth Model) | C19: =IFERROR(M9*(1+Assumptions!C39)/(Assumptions!C38-Assumptions!C39),0) -> 2410246961
B20: PV of Terminal Value ($) | C20: =C19*M14 -> 9.2925454e+08
B21: Implied Catalog Value ($) | C21: =C18+C20 -> 2396204303
B22: Implied LTM Multiple (Price / LTM Revenue) | C22: =IF(C8=0,0,C21/C8) -> 12.807078
B23: % of Value from Terminal Value | C23: =IF(C21=0,0,C20/C21) -> 0.38780272
B25: Market Benchmarks (Duetti/Billboard Music Finance Index)
B26: Catalog Age | C26: Masters Multiple | D26: Publishing Multiple
B27: 2-5 Years | C27: 3.5x - 9.5x | D27: 3.2x - 9.8x
B28: 5-10 Years | C28: 5.7x - 12.5x | D28: 6.1x - 13.9x
B29: 10+ Years | C29: 5.8x - 14x+ | D29: 8.7x - 16x+

Sheet Sensitivity
B1: Sensitivity Analysis — Catalog Valuation
B3: Implied Catalog Value ($)
B4: WACC ↓ / Terminal g → | C4: -0.05 | D4: -0.03 | E4: -0.02 | F4: -0.01 | G4: 0
B5: 0.08 | C5: =IFERROR('DCF Model'!C18+('DCF Model'!M9*(1+C4)/(B5-C4))/(1+B5)^10,"") -> 2465935786 | D5: =IFERROR('DCF Model'!C18+('DCF Model'!M9*(1+D4)/(B5-D4))/(1+B5)^10,"") -> 2672424763 | E5: =IFERROR('DCF Model'!C18+('DCF Model'!M9*(1+E4)/(B5-E4))/(1+B5)^10,"") -> 2806642598 | F5: =IFERROR('DCF Model'!C18+('DCF Model'!M9*(1+F4)/(B5-F4))/(1+B5)^10,"") -> 2970686619 | G5: =IFERROR('DCF Model'!C18+('DCF Model'!M9*(1+G4)/(B5-G4))/(1+B5)^10,"") -> 3175741645
B6: 0.1 | C6: =IFERROR('DCF Model'!C18+('DCF Model'!M9*(1+C4)/(B6-C4))/(1+B6)^10,"") -> 2187596141 | D6: =IFERROR('DCF Model'!C18+('DCF Model'!M9*(1+D4)/(B6-D4))/(1+B6)^10,"") -> 2315970395 | E6: =IFERROR('DCF Model'!C18+('DCF Model'!M9*(1+E4)/(B6-E4))/(1+B6)^10,"") -> 2396204303 | F6: =IFERROR('DCF Model'!C18+('DCF Model'!M9*(1+F4)/(B6-F4))/(1+B6)^10,"") -> 2491026195 | G6: =IFERROR('DCF Model'!C18+('DCF Model'!M9*(1+G4)/(B6-G4))/(1+B6)^10,"") -> 2604812466
B7: 0.12 | C7: =IFERROR('DCF Model'!C18+('DCF Model'!M9*(1+C4)/(B7-C4))/(1+B7)^10,"") -> 1997970120 | D7: =IFERROR('DCF Model'!C18+('DCF Model'!M9*(1+D4)/(B7-D4))/(1+B7)^10,"") -> 2081442794 | E7: =IFERROR('DCF Model'!C18+('DCF Model'!M9*(1+E4)/(B7-E4))/(1+B7)^10,"") -> 2132122632 | F7: =IFERROR('DCF Model'!C18+('DCF Model'!M9*(1+F4)/(B7-F4))/(1+B7)^10,"") -> 2190599368 | G7: =IFERROR('DCF Model'!C18+('DCF Model'!M9*(1+G4)/(B7-G4))/(1+B7)^10,"") -> 2258822226
B8: 0.14 | C8: =IFERROR('DCF Model'!C18+('DCF Model'!M9*(1+C4)/(B8-C4))/(1+B8)^10,"") -> 1865000291 | D8: =IFERROR('DCF Model'!C18+('DCF Model'!M9*(1+D4)/(B8-D4))/(1+B8)^10,"") -> 1921195659 | E8: =IFERROR('DCF Model'!C18+('DCF Model'!M9*(1+E4)/(B8-E4))/(1+B8)^10,"") -> 1954561660 | F8: =IFERROR('DCF Model'!C18+('DCF Model'!M9*(1+F4)/(B8-F4))/(1+B8)^10,"") -> 1992376460 | G8: =IFERROR('DCF Model'!C18+('DCF Model'!M9*(1+G4)/(B8-G4))/(1+B8)^10,"") -> 2035593374
B9: 0.16 | C9: =IFERROR('DCF Model'!C18+('DCF Model'!M9*(1+C4)/(B9-C4))/(1+B9)^10,"") -> 1769600078 | D9: =IFERROR('DCF Model'!C18+('DCF Model'!M9*(1+D4)/(B9-D4))/(1+B9)^10,"") -> 1808500285 | E9: =IFERROR('DCF Model'!C18+('DCF Model'!M9*(1+E4)/(B9-E4))/(1+B9)^10,"") -> 1831192073 | F9: =IFERROR('DCF Model'!C18+('DCF Model'!M9*(1+F4)/(B9-F4))/(1+B9)^10,"") -> 1856553482 | G9: =IFERROR('DCF Model'!C18+('DCF Model'!M9*(1+G4)/(B9-G4))/(1+B9)^10,"") -> 1885085068
B12: Implied LTM Multiple
B13: Yr1-3 Decay ↓ / PSR g → | C13: 0 | D13: 0.01 | E13: 0.02 | F13: 0.03 | G13: 0.04
B14: 0 | C14: =IFERROR(((1+B14)^1*(1+C13)^1/(1+Assumptions!C38)^1)+((1+B14)^2*(1+C13)^2/(1+Assumptions!C38)^2)+((1+B14)^3*(1+C13)^3/(1+Assumptions!C38)^3)+((1+B14)^4*(1+C13)^4/(1+Assumptions!C38)^4)+((1+B14)^5*(1+C13)^5/(1+Assumptions!C38)^5)+((1+B14)^6*(1+C13)^6/(1+Assumptions!C38)^6)+((1+B14)^7*(1+C13)^7/(1+Assumptions!C38)^7)+((1+B14)^8*(1+C13)^8/(1+Assumptions!C38)^8)+((1+B14)^9*(1+C13)^9/(1+Assumptions!C38)^9)+((1+B14)^10*(1+C13)^10/(1+Assumptions!C38)^10)+((1+B14)^10*(1+C13)^10*(1+Assumptions!C39)/(Assumptions!C38-Assumptions!C39))/(1+Assumptions!C38)^10,"") -> 9.2931706 | D14: =IFERROR(((1+B14)^1*(1+D13)^1/(1+Assumptions!C38)^1)+((1+B14)^2*(1+D13)^2/(1+Assumptions!C38)^2)+((1+B14)^3*(1+D13)^3/(1+Assumptions!C38)^3)+((1+B14)^4*(1+D13)^4/(1+Assumptions!C38)^4)+((1+B14)^5*(1+D13)^5/(1+Assumptions!C38)^5)+((1+B14)^6*(1+D13)^6/(1+Assumptions!C38)^6)+((1+B14)^7*(1+D13)^7/(1+Assumptions!C38)^7)+((1+B14)^8*(1+D13)^8/(1+Assumptions!C38)^8)+((1+B14)^9*(1+D13)^9/(1+Assumptions!C38)^9)+((1+B14)^10*(1+D13)^10/(1+Assumptions!C38)^10)+((1+B14)^10*(1+D13)^10*(1+Assumptions!C39)/(Assumptions!C38-Assumptions!C39))/(1+Assumptions!C38)^10,"") -> 9.9209233 | E14: =IFERROR(((1+B14)^1*(1+E13)^1/(1+Assumptions!C38)^1)+((1+B14)^2*(1+E13)^2/(1+Assumptions!C38)^2)+((1+B14)^3*(1+E13)^3/(1+Assumptions!C38)^3)+((1+B14)^4*(1+E13)^4/(1+Assumptions!C38)^4)+((1+B14)^5*(1+E13)^5/(1+Assumptions!C38)^5)+((1+B14)^6*(1+E13)^6/(1+Assumptions!C38)^6)+((1+B14)^7*(1+E13)^7/(1+Assumptions!C38)^7)+((1+B14)^8*(1+E13)^8/(1+Assumptions!C38)^8)+((1+B14)^9*(1+E13)^9/(1+Assumptions!C38)^9)+((1+B14)^10*(1+E13)^10/(1+Assumptions!C38)^10)+((1+B14)^10*(1+E13)^10*(1+Assumptions!C39)/(Assumptions!C38-Assumptions!C39))/(1+Assumptions!C38)^10,"") -> 10.595947 | F14: =IFERROR(((1+B14)^1*(1+F13)^1/(1+Assumptions!C38)^1)+((1+B14)^2*(1+F13)^2/(1+Assumptions!C38)^2)+((1+B14)^3*(1+F13)^3/(1+Assumptions!C38)^3)+((1+B14)^4*(1+F13)^4/(1+Assumptions!C38)^4)+((1+B14)^5*(1+F13)^5/(1+Assumptions!C38)^5)+((1+B14)^6*(1+F13)^6/(1+Assumptions!C38)^6)+((1+B14)^7*(1+F13)^7/(1+Assumptions!C38)^7)+((1+B14)^8*(1+F13)^8/(1+Assumptions!C38)^8)+((1+B14)^9*(1+F13)^9/(1+Assumptions!C38)^9)+((1+B14)^10*(1+F13)^10/(1+Assumptions!C38)^10)+((1+B14)^10*(1+F13)^10*(1+Assumptions!C39)/(Assumptions!C38-Assumptions!C39))/(1+Assumptions!C38)^10,"") -> 11.321716 | G14: =IFERROR(((1+B14)^1*(1+G13)^1/(1+Assumptions!C38)^1)+((1+B14)^2*(1+G13)^2/(1+Assumptions!C38)^2)+((1+B14)^3*(1+G13)^3/(1+Assumptions!C38)^3)+((1+B14)^4*(1+G13)^4/(1+Assumptions!C38)^4)+((1+B14)^5*(1+G13)^5/(1+Assumptions!C38)^5)+((1+B14)^6*(1+G13)^6/(1+Assumptions!C38)^6)+((1+B14)^7*(1+G13)^7/(1+Assumptions!C38)^7)+((1+B14)^8*(1+G13)^8/(1+Assumptions!C38)^8)+((1+B14)^9*(1+G13)^9/(1+Assumptions!C38)^9)+((1+B14)^10*(1+G13)^10/(1+Assumptions!C38)^10)+((1+B14)^10*(1+G13)^10*(1+Assumptions!C39)/(Assumptions!C38-Assumptions!C39))/(1+Assumptions!C38)^10,"") -> 12.101933
B15: -0.03 | C15: =IFERROR(((1+B15)^1*(1+C13)^1/(1+Assumptions!C38)^1)+((1+B15)^2*(1+C13)^2/(1+Assumptions!C38)^2)+((1+B15)^3*(1+C13)^3/(1+Assumptions!C38)^3)+((1+B15)^4*(1+C13)^4/(1+Assumptions!C38)^4)+((1+B15)^5*(1+C13)^5/(1+Assumptions!C38)^5)+((1+B15)^6*(1+C13)^6/(1+Assumptions!C38)^6)+((1+B15)^7*(1+C13)^7/(1+Assumptions!C38)^7)+((1+B15)^8*(1+C13)^8/(1+Assumptions!C38)^8)+((1+B15)^9*(1+C13)^9/(1+Assumptions!C38)^9)+((1+B15)^10*(1+C13)^10/(1+Assumptions!C38)^10)+((1+B15)^10*(1+C13)^10*(1+Assumptions!C39)/(Assumptions!C38-Assumptions!C39))/(1+Assumptions!C38)^10,"") -> 7.6620127 | D15: =IFERROR(((1+B15)^1*(1+D13)^1/(1+Assumptions!C38)^1)+((1+B15)^2*(1+D13)^2/(1+Assumptions!C38)^2)+((1+B15)^3*(1+D13)^3/(1+Assumptions!C38)^3)+((1+B15)^4*(1+D13)^4/(1+Assumptions!C38)^4)+((1+B15)^5*(1+D13)^5/(1+Assumptions!C38)^5)+((1+B15)^6*(1+D13)^6/(1+Assumptions!C38)^6)+((1+B15)^7*(1+D13)^7/(1+Assumptions!C38)^7)+((1+B15)^8*(1+D13)^8/(1+Assumptions!C38)^8)+((1+B15)^9*(1+D13)^9/(1+Assumptions!C38)^9)+((1+B15)^10*(1+D13)^10/(1+Assumptions!C38)^10)+((1+B15)^10*(1+D13)^10*(1+Assumptions!C39)/(Assumptions!C38-Assumptions!C39))/(1+Assumptions!C38)^10,"") -> 8.1509863 | E15: =IFERROR(((1+B15)^1*(1+E13)^1/(1+Assumptions!C38)^1)+((1+B15)^2*(1+E13)^2/(1+Assumptions!C38)^2)+((1+B15)^3*(1+E13)^3/(1+Assumptions!C38)^3)+((1+B15)^4*(1+E13)^4/(1+Assumptions!C38)^4)+((1+B15)^5*(1+E13)^5/(1+Assumptions!C38)^5)+((1+B15)^6*(1+E13)^6/(1+Assumptions!C38)^6)+((1+B15)^7*(1+E13)^7/(1+Assumptions!C38)^7)+((1+B15)^8*(1+E13)^8/(1+Assumptions!C38)^8)+((1+B15)^9*(1+E13)^9/(1+Assumptions!C38)^9)+((1+B15)^10*(1+E13)^10/(1+Assumptions!C38)^10)+((1+B15)^10*(1+E13)^10*(1+Assumptions!C39)/(Assumptions!C38-Assumptions!C39))/(1+Assumptions!C38)^10,"") -> 8.6757426 | F15: =IFERROR(((1+B15)^1*(1+F13)^1/(1+Assumptions!C38)^1)+((1+B15)^2*(1+F13)^2/(1+Assumptions!C38)^2)+((1+B15)^3*(1+F13)^3/(1+Assumptions!C38)^3)+((1+B15)^4*(1+F13)^4/(1+Assumptions!C38)^4)+((1+B15)^5*(1+F13)^5/(1+Assumptions!C38)^5)+((1+B15)^6*(1+F13)^6/(1+Assumptions!C38)^6)+((1+B15)^7*(1+F13)^7/(1+Assumptions!C38)^7)+((1+B15)^8*(1+F13)^8/(1+Assumptions!C38)^8)+((1+B15)^9*(1+F13)^9/(1+Assumptions!C38)^9)+((1+B15)^10*(1+F13)^10/(1+Assumptions!C38)^10)+((1+B15)^10*(1+F13)^10*(1+Assumptions!C39)/(Assumptions!C38-Assumptions!C39))/(1+Assumptions!C38)^10,"") -> 9.2388787 | G15: =IFERROR(((1+B15)^1*(1+G13)^1/(1+Assumptions!C38)^1)+((1+B15)^2*(1+G13)^2/(1+Assumptions!C38)^2)+((1+B15)^3*(1+G13)^3/(1+Assumptions!C38)^3)+((1+B15)^4*(1+G13)^4/(1+Assumptions!C38)^4)+((1+B15)^5*(1+G13)^5/(1+Assumptions!C38)^5)+((1+B15)^6*(1+G13)^6/(1+Assumptions!C38)^6)+((1+B15)^7*(1+G13)^7/(1+Assumptions!C38)^7)+((1+B15)^8*(1+G13)^8/(1+Assumptions!C38)^8)+((1+B15)^9*(1+G13)^9/(1+Assumptions!C38)^9)+((1+B15)^10*(1+G13)^10/(1+Assumptions!C38)^10)+((1+B15)^10*(1+G13)^10*(1+Assumptions!C39)/(Assumptions!C38-Assumptions!C39))/(1+Assumptions!C38)^10,"") -> 9.8431632
B16: -0.05 | C16: =IFERROR(((1+B16)^1*(1+C13)^1/(1+Assumptions!C38)^1)+((1+B16)^2*(1+C13)^2/(1+Assumptions!C38)^2)+((1+B16)^3*(1+C13)^3/(1+Assumptions!C38)^3)+((1+B16)^4*(1+C13)^4/(1+Assumptions!C38)^4)+((1+B16)^5*(1+C13)^5/(1+Assumptions!C38)^5)+((1+B16)^6*(1+C13)^6/(1+Assumptions!C38)^6)+((1+B16)^7*(1+C13)^7/(1+Assumptions!C38)^7)+((1+B16)^8*(1+C13)^8/(1+Assumptions!C38)^8)+((1+B16)^9*(1+C13)^9/(1+Assumptions!C38)^9)+((1+B16)^10*(1+C13)^10/(1+Assumptions!C38)^10)+((1+B16)^10*(1+C13)^10*(1+Assumptions!C39)/(Assumptions!C38-Assumptions!C39))/(1+Assumptions!C38)^10,"") -> 6.7565382 | D16: =IFERROR(((1+B16)^1*(1+D13)^1/(1+Assumptions!C38)^1)+((1+B16)^2*(1+D13)^2/(1+Assumptions!C38)^2)+((1+B16)^3*(1+D13)^3/(1+Assumptions!C38)^3)+((1+B16)^4*(1+D13)^4/(1+Assumptions!C38)^4)+((1+B16)^5*(1+D13)^5/(1+Assumptions!C38)^5)+((1+B16)^6*(1+D13)^6/(1+Assumptions!C38)^6)+((1+B16)^7*(1+D13)^7/(1+Assumptions!C38)^7)+((1+B16)^8*(1+D13)^8/(1+Assumptions!C38)^8)+((1+B16)^9*(1+D13)^9/(1+Assumptions!C38)^9)+((1+B16)^10*(1+D13)^10/(1+Assumptions!C38)^10)+((1+B16)^10*(1+D13)^10*(1+Assumptions!C39)/(Assumptions!C38-Assumptions!C39))/(1+Assumptions!C38)^10,"") -> 7.1702267 | E16: =IFERROR(((1+B16)^1*(1+E13)^1/(1+Assumptions!C38)^1)+((1+B16)^2*(1+E13)^2/(1+Assumptions!C38)^2)+((1+B16)^3*(1+E13)^3/(1+Assumptions!C38)^3)+((1+B16)^4*(1+E13)^4/(1+Assumptions!C38)^4)+((1+B16)^5*(1+E13)^5/(1+Assumptions!C38)^5)+((1+B16)^6*(1+E13)^6/(1+Assumptions!C38)^6)+((1+B16)^7*(1+E13)^7/(1+Assumptions!C38)^7)+((1+B16)^8*(1+E13)^8/(1+Assumptions!C38)^8)+((1+B16)^9*(1+E13)^9/(1+Assumptions!C38)^9)+((1+B16)^10*(1+E13)^10/(1+Assumptions!C38)^10)+((1+B16)^10*(1+E13)^10*(1+Assumptions!C39)/(Assumptions!C38-Assumptions!C39))/(1+Assumptions!C38)^10,"") -> 7.6135392 | F16: =IFERROR(((1+B16)^1*(1+F13)^1/(1+Assumptions!C38)^1)+((1+B16)^2*(1+F13)^2/(1+Assumptions!C38)^2)+((1+B16)^3*(1+F13)^3/(1+Assumptions!C38)^3)+((1+B16)^4*(1+F13)^4/(1+Assumptions!C38)^4)+((1+B16)^5*(1+F13)^5/(1+Assumptions!C38)^5)+((1+B16)^6*(1+F13)^6/(1+Assumptions!C38)^6)+((1+B16)^7*(1+F13)^7/(1+Assumptions!C38)^7)+((1+B16)^8*(1+F13)^8/(1+Assumptions!C38)^8)+((1+B16)^9*(1+F13)^9/(1+Assumptions!C38)^9)+((1+B16)^10*(1+F13)^10/(1+Assumptions!C38)^10)+((1+B16)^10*(1+F13)^10*(1+Assumptions!C39)/(Assumptions!C38-Assumptions!C39))/(1+Assumptions!C38)^10,"") -> 8.0886061 | G16: =IFERROR(((1+B16)^1*(1+G13)^1/(1+Assumptions!C38)^1)+((1+B16)^2*(1+G13)^2/(1+Assumptions!C38)^2)+((1+B16)^3*(1+G13)^3/(1+Assumptions!C38)^3)+((1+B16)^4*(1+G13)^4/(1+Assumptions!C38)^4)+((1+B16)^5*(1+G13)^5/(1+Assumptions!C38)^5)+((1+B16)^6*(1+G13)^6/(1+Assumptions!C38)^6)+((1+B16)^7*(1+G13)^7/(1+Assumptions!C38)^7)+((1+B16)^8*(1+G13)^8/(1+Assumptions!C38)^8)+((1+B16)^9*(1+G13)^9/(1+Assumptions!C38)^9)+((1+B16)^10*(1+G13)^10/(1+Assumptions!C38)^10)+((1+B16)^10*(1+G13)^10*(1+Assumptions!C39)/(Assumptions!C38-Assumptions!C39))/(1+Assumptions!C38)^10,"") -> 8.5976977
B17: -0.08 | C17: =IFERROR(((1+B17)^1*(1+C13)^1/(1+Assumptions!C38)^1)+((1+B17)^2*(1+C13)^2/(1+Assumptions!C38)^2)+((1+B17)^3*(1+C13)^3/(1+Assumptions!C38)^3)+((1+B17)^4*(1+C13)^4/(1+Assumptions!C38)^4)+((1+B17)^5*(1+C13)^5/(1+Assumptions!C38)^5)+((1+B17)^6*(1+C13)^6/(1+Assumptions!C38)^6)+((1+B17)^7*(1+C13)^7/(1+Assumptions!C38)^7)+((1+B17)^8*(1+C13)^8/(1+Assumptions!C38)^8)+((1+B17)^9*(1+C13)^9/(1+Assumptions!C38)^9)+((1+B17)^10*(1+C13)^10/(1+Assumptions!C38)^10)+((1+B17)^10*(1+C13)^10*(1+Assumptions!C39)/(Assumptions!C38-Assumptions!C39))/(1+Assumptions!C38)^10,"") -> 5.622842 | D17: =IFERROR(((1+B17)^1*(1+D13)^1/(1+Assumptions!C38)^1)+((1+B17)^2*(1+D13)^2/(1+Assumptions!C38)^2)+((1+B17)^3*(1+D13)^3/(1+Assumptions!C38)^3)+((1+B17)^4*(1+D13)^4/(1+Assumptions!C38)^4)+((1+B17)^5*(1+D13)^5/(1+Assumptions!C38)^5)+((1+B17)^6*(1+D13)^6/(1+Assumptions!C38)^6)+((1+B17)^7*(1+D13)^7/(1+Assumptions!C38)^7)+((1+B17)^8*(1+D13)^8/(1+Assumptions!C38)^8)+((1+B17)^9*(1+D13)^9/(1+Assumptions!C38)^9)+((1+B17)^10*(1+D13)^10/(1+Assumptions!C38)^10)+((1+B17)^10*(1+D13)^10*(1+Assumptions!C39)/(Assumptions!C38-Assumptions!C39))/(1+Assumptions!C38)^10,"") -> 5.9446547 | E17: =IFERROR(((1+B17)^1*(1+E13)^1/(1+Assumptions!C38)^1)+((1+B17)^2*(1+E13)^2/(1+Assumptions!C38)^2)+((1+B17)^3*(1+E13)^3/(1+Assumptions!C38)^3)+((1+B17)^4*(1+E13)^4/(1+Assumptions!C38)^4)+((1+B17)^5*(1+E13)^5/(1+Assumptions!C38)^5)+((1+B17)^6*(1+E13)^6/(1+Assumptions!C38)^6)+((1+B17)^7*(1+E13)^7/(1+Assumptions!C38)^7)+((1+B17)^8*(1+E13)^8/(1+Assumptions!C38)^8)+((1+B17)^9*(1+E13)^9/(1+Assumptions!C38)^9)+((1+B17)^10*(1+E13)^10/(1+Assumptions!C38)^10)+((1+B17)^10*(1+E13)^10*(1+Assumptions!C39)/(Assumptions!C38-Assumptions!C39))/(1+Assumptions!C38)^10,"") -> 6.288675 | F17: =IFERROR(((1+B17)^1*(1+F13)^1/(1+Assumptions!C38)^1)+((1+B17)^2*(1+F13)^2/(1+Assumptions!C38)^2)+((1+B17)^3*(1+F13)^3/(1+Assumptions!C38)^3)+((1+B17)^4*(1+F13)^4/(1+Assumptions!C38)^4)+((1+B17)^5*(1+F13)^5/(1+Assumptions!C38)^5)+((1+B17)^6*(1+F13)^6/(1+Assumptions!C38)^6)+((1+B17)^7*(1+F13)^7/(1+Assumptions!C38)^7)+((1+B17)^8*(1+F13)^8/(1+Assumptions!C38)^8)+((1+B17)^9*(1+F13)^9/(1+Assumptions!C38)^9)+((1+B17)^10*(1+F13)^10/(1+Assumptions!C38)^10)+((1+B17)^10*(1+F13)^10*(1+Assumptions!C39)/(Assumptions!C38-Assumptions!C39))/(1+Assumptions!C38)^10,"") -> 6.6564746 | G17: =IFERROR(((1+B17)^1*(1+G13)^1/(1+Assumptions!C38)^1)+((1+B17)^2*(1+G13)^2/(1+Assumptions!C38)^2)+((1+B17)^3*(1+G13)^3/(1+Assumptions!C38)^3)+((1+B17)^4*(1+G13)^4/(1+Assumptions!C38)^4)+((1+B17)^5*(1+G13)^5/(1+Assumptions!C38)^5)+((1+B17)^6*(1+G13)^6/(1+Assumptions!C38)^6)+((1+B17)^7*(1+G13)^7/(1+Assumptions!C38)^7)+((1+B17)^8*(1+G13)^8/(1+Assumptions!C38)^8)+((1+B17)^9*(1+G13)^9/(1+Assumptions!C38)^9)+((1+B17)^10*(1+G13)^10/(1+Assumptions!C38)^10)+((1+B17)^10*(1+G13)^10*(1+Assumptions!C39)/(Assumptions!C38-Assumptions!C39))/(1+Assumptions!C38)^10,"") -> 7.0497282
B18: -0.1 | C18: =IFERROR(((1+B18)^1*(1+C13)^1/(1+Assumptions!C38)^1)+((1+B18)^2*(1+C13)^2/(1+Assumptions!C38)^2)+((1+B18)^3*(1+C13)^3/(1+Assumptions!C38)^3)+((1+B18)^4*(1+C13)^4/(1+Assumptions!C38)^4)+((1+B18)^5*(1+C13)^5/(1+Assumptions!C38)^5)+((1+B18)^6*(1+C13)^6/(1+Assumptions!C38)^6)+((1+B18)^7*(1+C13)^7/(1+Assumptions!C38)^7)+((1+B18)^8*(1+C13)^8/(1+Assumptions!C38)^8)+((1+B18)^9*(1+C13)^9/(1+Assumptions!C38)^9)+((1+B18)^10*(1+C13)^10/(1+Assumptions!C38)^10)+((1+B18)^10*(1+C13)^10*(1+Assumptions!C39)/(Assumptions!C38-Assumptions!C39))/(1+Assumptions!C38)^10,"") -> 4.9929123 | D18: =IFERROR(((1+B18)^1*(1+D13)^1/(1+Assumptions!C38)^1)+((1+B18)^2*(1+D13)^2/(1+Assumptions!C38)^2)+((1+B18)^3*(1+D13)^3/(1+Assumptions!C38)^3)+((1+B18)^4*(1+D13)^4/(1+Assumptions!C38)^4)+((1+B18)^5*(1+D13)^5/(1+Assumptions!C38)^5)+((1+B18)^6*(1+D13)^6/(1+Assumptions!C38)^6)+((1+B18)^7*(1+D13)^7/(1+Assumptions!C38)^7)+((1+B18)^8*(1+D13)^8/(1+Assumptions!C38)^8)+((1+B18)^9*(1+D13)^9/(1+Assumptions!C38)^9)+((1+B18)^10*(1+D13)^10/(1+Assumptions!C38)^10)+((1+B18)^10*(1+D13)^10*(1+Assumptions!C39)/(Assumptions!C38-Assumptions!C39))/(1+Assumptions!C38)^10,"") -> 5.2651598 | E18: =IFERROR(((1+B18)^1*(1+E13)^1/(1+Assumptions!C38)^1)+((1+B18)^2*(1+E13)^2/(1+Assumptions!C38)^2)+((1+B18)^3*(1+E13)^3/(1+Assumptions!C38)^3)+((1+B18)^4*(1+E13)^4/(1+Assumptions!C38)^4)+((1+B18)^5*(1+E13)^5/(1+Assumptions!C38)^5)+((1+B18)^6*(1+E13)^6/(1+Assumptions!C38)^6)+((1+B18)^7*(1+E13)^7/(1+Assumptions!C38)^7)+((1+B18)^8*(1+E13)^8/(1+Assumptions!C38)^8)+((1+B18)^9*(1+E13)^9/(1+Assumptions!C38)^9)+((1+B18)^10*(1+E13)^10/(1+Assumptions!C38)^10)+((1+B18)^10*(1+E13)^10*(1+Assumptions!C39)/(Assumptions!C38-Assumptions!C39))/(1+Assumptions!C38)^10,"") -> 5.5556752 | F18: =IFERROR(((1+B18)^1*(1+F13)^1/(1+Assumptions!C38)^1)+((1+B18)^2*(1+F13)^2/(1+Assumptions!C38)^2)+((1+B18)^3*(1+F13)^3/(1+Assumptions!C38)^3)+((1+B18)^4*(1+F13)^4/(1+Assumptions!C38)^4)+((1+B18)^5*(1+F13)^5/(1+Assumptions!C38)^5)+((1+B18)^6*(1+F13)^6/(1+Assumptions!C38)^6)+((1+B18)^7*(1+F13)^7/(1+Assumptions!C38)^7)+((1+B18)^8*(1+F13)^8/(1+Assumptions!C38)^8)+((1+B18)^9*(1+F13)^9/(1+Assumptions!C38)^9)+((1+B18)^10*(1+F13)^10/(1+Assumptions!C38)^10)+((1+B18)^10*(1+F13)^10*(1+Assumptions!C39)/(Assumptions!C38-Assumptions!C39))/(1+Assumptions!C38)^10,"") -> 5.8657362 | G18: =IFERROR(((1+B18)^1*(1+G13)^1/(1+Assumptions!C38)^1)+((1+B18)^2*(1+G13)^2/(1+Assumptions!C38)^2)+((1+B18)^3*(1+G13)^3/(1+Assumptions!C38)^3)+((1+B18)^4*(1+G13)^4/(1+Assumptions!C38)^4)+((1+B18)^5*(1+G13)^5/(1+Assumptions!C38)^5)+((1+B18)^6*(1+G13)^6/(1+Assumptions!C38)^6)+((1+B18)^7*(1+G13)^7/(1+Assumptions!C38)^7)+((1+B18)^8*(1+G13)^8/(1+Assumptions!C38)^8)+((1+B18)^9*(1+G13)^9/(1+Assumptions!C38)^9)+((1+B18)^10*(1+G13)^10/(1+Assumptions!C38)^10)+((1+B18)^10*(1+G13)^10*(1+Assumptions!C39)/(Assumptions!C38-Assumptions!C39))/(1+Assumptions!C38)^10,"") -> 6.1967035

Sheet Methodology
B1: Model Methodology & Key Concepts
B3: 1. Per-Stream Rates (PSRs)
B4: A Per-Stream Rate is the amount of money paid to right's holders a song is played on DSP's. Many DSP's pay various royalties like Apple Music ($0.01) and Spotify ($0.004) since Apple Music doesn't have a free tier. The mix that Drake has through all the DSP's results in a PSR around $0.005. PSR's are going up because of the fact that DSP's are raising their subscription prices. The Duetti Music Economics Report also talks about how 1000 streams generated an average of $3.41 in 2024.
B6: 2. DSP Mix
B7: The distribution of Drake's streams across various platforms matters for revenue because of the fact that many of the streams are on Spotify but Apple Music contributes more revenue because it has a higher PSR. This shows why DSP analysis is very important for Duetti's underwriting processes since many artists can have various streams with very similar revnue profiles based on the platform distribution.
B9: 3. Stream Decay Curves
B10: Drake's catalog shows very unusually low decay. He has 17.6B Spotify streams in 2025 without a single solo album release. As per the Duetti/Billboard Music Finance index, younger catalogs show much more steeper decay curves. Drake's much more older hits (Take Care era, 10+ years) have essentially steadied, making his catalog a very good asset.
B12: 4. Catalog Multiples & Market Benchmarks
B13: The Billboard/Duetti Music Finance Index shows that masters which are trading at 3.5x-13x+ LTM revenue depending on age and stability. Drake's weighted average catalog (low volatility & massive scale) would trade on the premium end. His $400M UMG deal, against estimated $50M annual catalog revenue, indicates that there is roughly an 8x multiple which is consistent with a premium 5-10 year catalog.
B15: 5. DCF Methodology
B16: A 10% WACC gets used and that reflects Drake's lower risk: large scale, very diversified across DSP's, a proven track record, and classic hits. The terminal value uses the -2% terminal growth rate. For Duetti's more usual indie artist deals, the WACC would be higher since here would be smaller, more volatile catalogs.
B18: 6. Rights Types (Masters vs. Publishing)
... B28: Kworb.net (Spotify chart data), Chartmasters.org (all-time stream totals), AllHipHop/HotNewHipHop (2025 streaming milestones), Duetti Music Economics Report 2024, Duetti/Billboard Music Finance Index, Celebrity Net Worth (UMG deal valuation), Royalty Exchange (transaction multiples), Spotify Wrapped 2025. (All sourced from Perplexity and Claude)

Sheet PSR Reference
B1: Per-Stream Rate Reference Table (2024-2025 Estimates)
B3: DSP | C3: Low Estimate ($) | D3: High Estimate ($) | E3: Notes
B4: Spotify | C4: 0.003 | D4: 0.005 | E4: Pro-rata model; varies by country, free vs premium
B5: Apple Music | C5: 0.008 | D5: 0.012 | E5: Higher PSR; all paid subscribers, no free tier
B6: YouTube Music | C6: 0.001 | D6: 0.003 | E6: Includes ad-supported; lower blended rate
B7: Amazon Music | C7: 0.004 | D7: 0.005 | E7: Mix of Unlimited, Prime, and free tiers
B8: Tidal | C8: 0.01 | D8: 0.013 | E8: Highest PSR; smaller user base, premium focus
B9: Deezer | C9: 0.001 | D9: 0.004 | E9: Artist-centric model as of 2024
B10: SoundCloud | C10: 0.002 | D10: 0.004 | E10: Fan-powered royalties for eligible artists
B11: Pandora | C11: 0.001 | D11: 0.002 | E11: Non-interactive radio model
B13: Source: Duetti Music Economics Report, Royalty Exchange, industry estimates
B14: Note: Actual PSRs vary by territory, subscription tier, and time period. These are US-weighted averages.
